questdb/__init__.py
questdb/arrow_c_data_interface.h
questdb/arrow_c_data_interface.pxd
questdb/conf_str.h
questdb/conf_str.pxd
questdb/dataframe.html
questdb/dataframe.md
questdb/dataframe.pxi
questdb/extra_cpython.pxd
questdb/extra_numpy.pxd
questdb/ingress.c
questdb/ingress.cpython-311-x86_64-linux-gnu.so
questdb/ingress.html
questdb/ingress.pyi
questdb/ingress.pyx
questdb/ingress_helper.inc
questdb/ingress_helper.pxd
questdb/line_sender.pxd
questdb/rpyutils.pxd
questdb-4.0.0.dist-info/METADATA
questdb-4.0.0.dist-info/WHEEL
questdb-4.0.0.dist-info/top_level.txt
questdb-4.0.0.dist-info/RECORD
questdb-4.0.0.dist-info/licenses/LICENSE.txt
