Metadata-Version: 2.4
Name: questdb
Version: 4.0.0
Summary: QuestDB client library for Python
Author-email: Adam Cimarosti <adam@questdb.com>
License-Expression: Apache-2.0
Project-URL: Homepage, https://questdb.io/
Project-URL: Changelog, https://py-questdb-client.readthedocs.io/en/latest/changelog.html
Project-URL: Documentation, https://py-questdb-client.readthedocs.io/en/latest/index.html
Project-URL: Source, https://github.com/questdb/py-questdb-client/
Project-URL: Tracker, https://github.com/questdb/py-questdb-client/issues
Project-URL: Community, http://community.questdb.io
Platform: any
Classifier: Development Status :: 5 - Production/Stable
Classifier: Environment :: Plugins
Classifier: Intended Audience :: Developers
Classifier: Programming Language :: Python
Classifier: Programming Language :: Python :: 3
Classifier: Programming Language :: Cython
Classifier: Programming Language :: Rust
Classifier: Topic :: Software Development :: Libraries
Classifier: Topic :: System :: Networking
Classifier: Topic :: Database :: Front-Ends
Classifier: Topic :: Scientific/Engineering
Requires-Python: >=3.8
License-File: LICENSE.txt
Requires-Dist: numpy>=1.21.0
Provides-Extra: publish
Requires-Dist: twine; extra == "publish"
Requires-Dist: wheel; extra == "publish"
Provides-Extra: ci
Requires-Dist: cibuildwheel; extra == "ci"
Provides-Extra: dataframe
Requires-Dist: pandas; extra == "dataframe"
Requires-Dist: pyarrow; extra == "dataframe"
Requires-Dist: numpy; extra == "dataframe"
Dynamic: license-file
Dynamic: platform
Dynamic: requires-python
